wecs/__init__.py
wecs/aspects.py
wecs/boilerplate.py
wecs/core.py
wecs/equipment.py
wecs/graphviz.py
wecs/inventory.py
wecs/repl.py
wecs/rooms.py
wecs/mechanics/__init__.py
wecs/mechanics/clock.py
wecs/panda3d/__init__.py
wecs/panda3d/ai.py
wecs/panda3d/animation.py
wecs/panda3d/avatar_ui.py
wecs/panda3d/behavior_trees.py
wecs/panda3d/camera.py
wecs/panda3d/character.py
wecs/panda3d/clock.py
wecs/panda3d/constants.py
wecs/panda3d/core.py
wecs/panda3d/debug.py
wecs/panda3d/gravity.py
wecs/panda3d/input.py
wecs/panda3d/map_muncher.py
wecs/panda3d/mouseover.py
wecs/panda3d/prototype.py
wecs/panda3d/spawnpoints.py
wecs-0.2.1a0.dist-info/LICENSE
wecs-0.2.1a0.dist-info/METADATA
wecs-0.2.1a0.dist-info/WHEEL
wecs-0.2.1a0.dist-info/top_level.txt
wecs-0.2.1a0.dist-info/RECORD
